RunwayLib/__init__.py
RunwayLib/errorbox.py
RunwayLib/hello.py
RunwayLib/luck.py
RunwayLib/minestats.py
RunwayLib/server.py
RunwayLib/test.py
RunwayLib-0.4.4.dist-info/LICENSE
RunwayLib-0.4.4.dist-info/METADATA
RunwayLib-0.4.4.dist-info/WHEEL
RunwayLib-0.4.4.dist-info/top_level.txt
RunwayLib-0.4.4.dist-info/RECORD
