Metadata-Version: 2.1
Name: RunwayLib
Version: 0.4.4
Summary: A library for a server
Author: Parsa
Author-email: your-email@example.com
Classifier: Programming Language :: Python :: 3
Classifier: License :: OSI Approved :: MIT License
Classifier: Operating System :: OS Independent
Requires-Python: >=3.6
License-File: LICENSE
